<?xml version="1.0" encoding="UTF-8"?>
<employees>

    <employee id="101">
        <name>Shehryar</name>
        <room>201</room>
    </employee>

    <employee id="102">
        <name>Sara</name>
        <room>202</room>
    </employee>

    <employee id="103">
        <name>Amy</name>
        <room>203</room>
    </employee>

    <employee id="104">
        <name>John</name>
        <room>204</room>
    </employee>

    <employee id="105">
        <name>Lisa</name>
        <room>205</room>
    </employee>

    <employee id="106">
        <name>Khalid</name>
        <room>206</room>
    </employee>

</employees>